MANIFEST.in
README.md
clusterapp.py
clustermgr-cli
setup.py
clustermgr/__init__.py
clustermgr/application.py
clustermgr/config.py
clustermgr/extensions.py
clustermgr/forms.py
clustermgr/get_remote_stats.py
clustermgr/models.py
clustermgr/monitoring_defs.py
clustermgr/weblogger.py
clustermgr.egg-info/PKG-INFO
clustermgr.egg-info/SOURCES.txt
clustermgr.egg-info/dependency_links.txt
clustermgr.egg-info/not-zip-safe
clustermgr.egg-info/requires.txt
clustermgr.egg-info/top_level.txt
clustermgr/core/Properties.py
clustermgr/core/__init__.py
clustermgr/core/change_gluu_host.py
clustermgr/core/clustermgr_installer.py
clustermgr/core/ldap_functions.py
clustermgr/core/ldifschema_utils.py
clustermgr/core/license.py
clustermgr/core/msgcon.py
clustermgr/core/ox11.py
clustermgr/core/remote.py
clustermgr/core/utils.py
clustermgr/migrations/alembic.ini
clustermgr/migrations/env.py
clustermgr/migrations/script.py.mako
clustermgr/migrations/versions/049e02a8d91d_add_redis_password.py
clustermgr/migrations/versions/0688ae3baa88_add_offline_installation_fields.py
clustermgr/migrations/versions/0c35f58a2e73_.py
clustermgr/migrations/versions/0e7453df1644_update_keyrotation.py
clustermgr/migrations/versions/18ccbe0eda39_add_installed_flag_to_cacheserver.py
clustermgr/migrations/versions/22f6c85b4b24_.py
clustermgr/migrations/versions/2926b8ffa2f0_.py
clustermgr/migrations/versions/2a0c96ff52f6_add_admin_email_field.py
clustermgr/migrations/versions/496b3a1cbc65_add_ldap_update_period_unit_to_.py
clustermgr/migrations/versions/4fca7c65b3df_add_nginx_ip_column_to_appconfig.py
clustermgr/migrations/versions/5246a3f7a7e4_consolidated_all_server_models.py
clustermgr/migrations/versions/54968b4c309f_add_latest_version_to_appconfiguration.py
clustermgr/migrations/versions/55c791eac900_.py
clustermgr/migrations/versions/5cc68648b63e_add_monitoring_for_servers.py
clustermgr/migrations/versions/601d70820f5d_add_modify_hosts_to_appconfiguration.py
clustermgr/migrations/versions/6f0d7d321e8b_remove_cache_host_cache_ip_and_install_.py
clustermgr/migrations/versions/8385d7dcdcdc_add_filebeat_column.py
clustermgr/migrations/versions/867fa650eacd_add_nginx_os_type.py
